area/__init__.py
area/shapes.py
area_jiya-0.1.dist-info/METADATA
area_jiya-0.1.dist-info/WHEEL
area_jiya-0.1.dist-info/top_level.txt
area_jiya-0.1.dist-info/RECORD
